{"2020-12-27": {"80": {"n_dose1": 0, "n_cum_dose1": 0, "taux": 0.0}, "39": {"n_dose1": 0, "n_cum_dose1": 0, "taux": 0.0}, "24": {"n_dose1": 0, "n_cum_dose1": 0, "taux": 0.0}, "74": {"n_dose1": 0, "n_cum_dose1": 0, "taux": 0.0}, "29": {"n_dose1": 0, "n_cum_dose1": 0, "taux": 0.0}, "0": {"n_dose1": 0, "n_cum_dose1": 0, "taux": 0.0}, "59": {"n_dose1": 0, "n_cum_dose1": 0, "taux": 0.0}, "79": {"n_dose1": 0, "n_cum_dose1": 0, "taux": 0.0}, "64": {"n_dose1": 0, "n_cum_dose1": 0, "taux": 0.0}, "69": {"n_dose1": 0, "n_cum_dose1": 0, "taux": 0.0}, "49": {"n_dose1": 0, "n_cum_dose1": 0, "taux": 0.0}}, "2020-12-28": {"80": {"n_dose1": 0, "n_cum_dose1": 0, "taux": 0.0}, "39": {"n_dose1": 0, "n_cum_dose1": 0, "taux": 0.0}, "24": {"n_dose1": 0, "n_cum_dose1": 0, "taux": 0.0}, "74": {"n_dose1": 0, "n_cum_dose1": 0, "taux": 0.0}, "29": {"n_dose1": 0, "n_cum_dose1": 0, "taux": 0.0}, "0": {"n_dose1": 0, "n_cum_dose1": 0, "taux": 0.0}, "59": {"n_dose1": 0, "n_cum_dose1": 0, "taux": 0.0}, "79": {"n_dose1": 0, "n_cum_dose1": 0, "taux": 0.0}, "64": {"n_dose1": 0, "n_cum_dose1": 0, "taux": 0.0}, "69": {"n_dose1": 0, "n_cum_dose1": 0, "taux": 0.0}, "49": {"n_dose1": 0, "n_cum_dose1": 0, "taux": 0.0}}, "2020-12-29": {"80": {"n_dose1": 0, "n_cum_dose1": 0, "taux": 0.0}, "39": {"n_dose1": 0, "n_cum_dose1": 0, "taux": 0.0}, "24": {"n_dose1": 0, "n_cum_dose1": 0, "taux": 0.0}, "74": {"n_dose1": 0, "n_cum_dose1": 0, "taux": 0.0}, "29": {"n_dose1": 0, "n_cum_dose1": 0, "taux": 0.0}, "0": {"n_dose1": 0, "n_cum_dose1": 0, "taux": 0.0}, "59": {"n_dose1": 0, "n_cum_dose1": 0, "taux": 0.0}, "79": {"n_dose1": 0, "n_cum_dose1": 0, "taux": 0.0}, "64": {"n_dose1": 0, "n_cum_dose1": 0, "taux": 0.0}, "69": {"n_dose1": 0, "n_cum_dose1": 0, "taux": 0.0}, "49": {"n_dose1": 0, "n_cum_dose1": 0, "taux": 0.0}}, "2020-12-30": {"80": {"n_dose1": 0, "n_cum_dose1": 0, "taux": 0.0}, "39": {"n_dose1": 0, "n_cum_dose1": 0, "taux": 0.0}, "24": {"n_dose1": 0, "n_cum_dose1": 0, "taux": 0.0}, "74": {"n_dose1": 0, "n_cum_dose1": 0, "taux": 0.0}, "29": {"n_dose1": 0, "n_cum_dose1": 0, "taux": 0.0}, "0": {"n_dose1": 0, "n_cum_dose1": 0, "taux": 0.0}, "59": {"n_dose1": 0, "n_cum_dose1": 0, "taux": 0.0}, "79": {"n_dose1": 0, "n_cum_dose1": 0, "taux": 0.0}, "64": {"n_dose1": 0, "n_cum_dose1": 0, "taux": 0.0}, "69": {"n_dose1": 0, "n_cum_dose1": 0, "taux": 0.0}, "49": {"n_dose1": 0, "n_cum_dose1": 0, "taux": 0.0}}, "2020-12-31": {"80": {"n_dose1": 1, "n_cum_dose1": 1, "taux": "0.00"}, "39": {"n_dose1": 0, "n_cum_dose1": 0, "taux": 0.0}, "24": {"n_dose1": 0, "n_cum_dose1": 0, "taux": 0.0}, "74": {"n_dose1": 2, "n_cum_dose1": 2, "taux": "0.00"}, "29": {"n_dose1": 0, "n_cum_dose1": 0, "taux": 0.0}, "0": {"n_dose1": 5, "n_cum_dose1": 5, "taux": "0.00"}, "59": {"n_dose1": 0, "n_cum_dose1": 0, "taux": 0.0}, "79": {"n_dose1": 1, "n_cum_dose1": 1, "taux": "0.00"}, "64": {"n_dose1": 1, "n_cum_dose1": 1, "taux": "0.00"}, "69": {"n_dose1": 0, "n_cum_dose1": 0, "taux": 0.0}, "49": {"n_dose1": 0, "n_cum_dose1": 0, "taux": 0.0}}, "2021-01-01": {"80": {"n_dose1": 0, "n_cum_dose1": 0, "taux": 0.0}, "39": {"n_dose1": 0, "n_cum_dose1": 0, "taux": 0.0}, "24": {"n_dose1": 0, "n_cum_dose1": 0, "taux": 0.0}, "74": {"n_dose1": 0, "n_cum_dose1": 0, "taux": 0.0}, "29": {"n_dose1": 0, "n_cum_dose1": 0, "taux": 0.0}, "0": {"n_dose1": 0, "n_cum_dose1": 0, "taux": 0.0}, "59": {"n_dose1": 0, "n_cum_dose1": 0, "taux": 0.0}, "79": {"n_dose1": 0, "n_cum_dose1": 0, "taux": 0.0}, "64": {"n_dose1": 0, "n_cum_dose1": 0, "taux": 0.0}, "69": {"n_dose1": 0, "n_cum_dose1": 0, "taux": 0.0}, "49": {"n_dose1": 0, "n_cum_dose1": 0, "taux": 0.0}}, "2021-01-02": {"80": {"n_dose1": 0, "n_cum_dose1": 0, "taux": 0.0}, "39": {"n_dose1": 0, "n_cum_dose1": 0, "taux": 0.0}, "24": {"n_dose1": 0, "n_cum_dose1": 0, "taux": 0.0}, "74": {"n_dose1": 0, "n_cum_dose1": 0, "taux": 0.0}, "29": {"n_dose1": 0, "n_cum_dose1": 0, "taux": 0.0}, "0": {"n_dose1": 0, "n_cum_dose1": 0, "taux": 0.0}, "59": {"n_dose1": 0, "n_cum_dose1": 0, "taux": 0.0}, "79": {"n_dose1": 0, "n_cum_dose1": 0, "taux": 0.0}, "64": {"n_dose1": 0, "n_cum_dose1": 0, "taux": 0.0}, "69": {"n_dose1": 0, "n_cum_dose1": 0, "taux": 0.0}, "49": {"n_dose1": 0, "n_cum_dose1": 0, "taux": 0.0}}, "2021-01-03": {"80": {"n_dose1": 0, "n_cum_dose1": 0, "taux": 0.0}, "39": {"n_dose1": 0, "n_cum_dose1": 0, "taux": 0.0}, "24": {"n_dose1": 0, "n_cum_dose1": 0, "taux": 0.0}, "74": {"n_dose1": 0, "n_cum_dose1": 0, "taux": 0.0}, "29": {"n_dose1": 0, "n_cum_dose1": 0, "taux": 0.0}, "0": {"n_dose1": 0, "n_cum_dose1": 0, "taux": 0.0}, "59": {"n_dose1": 0, "n_cum_dose1": 0, "taux": 0.0}, "79": {"n_dose1": 0, "n_cum_dose1": 0, "taux": 0.0}, "64": {"n_dose1": 0, "n_cum_dose1": 0, "taux": 0.0}, "69": {"n_dose1": 0, "n_cum_dose1": 0, "taux": 0.0}, "49": {"n_dose1": 0, "n_cum_dose1": 0, "taux": 0.0}}, "2021-01-04": {"80": {"n_dose1": 34, "n_cum_dose1": 35, "taux": "0.05"}, "39": {"n_dose1": 5, "n_cum_dose1": 5, "taux": "0.00"}, "24": {"n_dose1": 0, "n_cum_dose1": 0, "taux": 0.0}, "74": {"n_dose1": 13, "n_cum_dose1": 15, "taux": "0.03"}, "29": {"n_dose1": 0, "n_cum_dose1": 0, "taux": 0.0}, "0": {"n_dose1": 162, "n_cum_dose1": 167, "taux": "0.01"}, "59": {"n_dose1": 57, "n_cum_dose1": 57, "taux": "0.04"}, "79": {"n_dose1": 5, "n_cum_dose1": 6, "taux": "0.02"}, "64": {"n_dose1": 28, "n_cum_dose1": 29, "taux": "0.04"}, "69": {"n_dose1": 7, "n_cum_dose1": 7, "taux": "0.01"}, "49": {"n_dose1": 13, "n_cum_dose1": 13, "taux": "0.01"}}, "2021-01-05": {"80": {"n_dose1": 39, "n_cum_dose1": 74, "taux": "0.11"}, "39": {"n_dose1": 3, "n_cum_dose1": 8, "taux": "0.01"}, "24": {"n_dose1": 1, "n_cum_dose1": 1, "taux": "0.00"}, "74": {"n_dose1": 14, "n_cum_dose1": 29, "taux": "0.06"}, "29": {"n_dose1": 3, "n_cum_dose1": 3, "taux": "0.00"}, "0": {"n_dose1": 252, "n_cum_dose1": 419, "taux": "0.03"}, "59": {"n_dose1": 86, "n_cum_dose1": 143, "taux": "0.09"}, "79": {"n_dose1": 5, "n_cum_dose1": 11, "taux": "0.03"}, "64": {"n_dose1": 55, "n_cum_dose1": 84, "taux": "0.12"}, "69": {"n_dose1": 30, "n_cum_dose1": 37, "taux": "0.05"}, "49": {"n_dose1": 16, "n_cum_dose1": 29, "taux": "0.02"}}, "2021-01-06": {"80": {"n_dose1": 62, "n_cum_dose1": 136, "taux": "0.20"}, "39": {"n_dose1": 11, "n_cum_dose1": 19, "taux": "0.01"}, "24": {"n_dose1": 1, "n_cum_dose1": 2, "taux": "0.00"}, "74": {"n_dose1": 25, "n_cum_dose1": 54, "taux": "0.11"}, "29": {"n_dose1": 3, "n_cum_dose1": 6, "taux": "0.01"}, "0": {"n_dose1": 364, "n_cum_dose1": 783, "taux": "0.06"}, "59": {"n_dose1": 106, "n_cum_dose1": 249, "taux": "0.15"}, "79": {"n_dose1": 24, "n_cum_dose1": 35, "taux": "0.09"}, "64": {"n_dose1": 76, "n_cum_dose1": 160, "taux": "0.22"}, "69": {"n_dose1": 41, "n_cum_dose1": 78, "taux": "0.11"}, "49": {"n_dose1": 14, "n_cum_dose1": 43, "taux": "0.03"}}, "2021-01-07": {"80": {"n_dose1": 37, "n_cum_dose1": 173, "taux": "0.26"}, "39": {"n_dose1": 35, "n_cum_dose1": 54, "taux": "0.03"}, "24": {"n_dose1": 5, "n_cum_dose1": 7, "taux": "0.00"}, "74": {"n_dose1": 36, "n_cum_dose1": 90, "taux": "0.18"}, "29": {"n_dose1": 8, "n_cum_dose1": 14, "taux": "0.02"}, "0": {"n_dose1": 610, "n_cum_dose1": 1393, "taux": "0.11"}, "59": {"n_dose1": 245, "n_cum_dose1": 494, "taux": "0.30"}, "79": {"n_dose1": 24, "n_cum_dose1": 59, "taux": "0.15"}, "64": {"n_dose1": 109, "n_cum_dose1": 269, "taux": "0.37"}, "69": {"n_dose1": 59, "n_cum_dose1": 137, "taux": "0.20"}, "49": {"n_dose1": 52, "n_cum_dose1": 95, "taux": "0.06"}}, "2021-01-08": {"80": {"n_dose1": 29, "n_cum_dose1": 202, "taux": "0.30"}, "39": {"n_dose1": 44, "n_cum_dose1": 98, "taux": "0.06"}, "24": {"n_dose1": 6, "n_cum_dose1": 13, "taux": "0.01"}, "74": {"n_dose1": 46, "n_cum_dose1": 136, "taux": "0.27"}, "29": {"n_dose1": 10, "n_cum_dose1": 24, "taux": "0.03"}, "0": {"n_dose1": 638, "n_cum_dose1": 2031, "taux": "0.16"}, "59": {"n_dose1": 228, "n_cum_dose1": 722, "taux": "0.44"}, "79": {"n_dose1": 23, "n_cum_dose1": 82, "taux": "0.21"}, "64": {"n_dose1": 123, "n_cum_dose1": 392, "taux": "0.54"}, "69": {"n_dose1": 72, "n_cum_dose1": 209, "taux": "0.31"}, "49": {"n_dose1": 57, "n_cum_dose1": 152, "taux": "0.09"}}, "2021-01-09": {"80": {"n_dose1": 0, "n_cum_dose1": 0, "taux": 0.0}, "39": {"n_dose1": 0, "n_cum_dose1": 0, "taux": 0.0}, "24": {"n_dose1": 0, "n_cum_dose1": 0, "taux": 0.0}, "74": {"n_dose1": 0, "n_cum_dose1": 0, "taux": 0.0}, "29": {"n_dose1": 0, "n_cum_dose1": 0, "taux": 0.0}, "0": {"n_dose1": 1, "n_cum_dose1": 2032, "taux": "0.16"}, "59": {"n_dose1": 0, "n_cum_dose1": 0, "taux": 0.0}, "79": {"n_dose1": 0, "n_cum_dose1": 0, "taux": 0.0}, "64": {"n_dose1": 1, "n_cum_dose1": 393, "taux": "0.54"}, "69": {"n_dose1": 0, "n_cum_dose1": 0, "taux": 0.0}, "49": {"n_dose1": 0, "n_cum_dose1": 0, "taux": 0.0}}, "2021-01-10": {"80": {"n_dose1": 0, "n_cum_dose1": 0, "taux": 0.0}, "39": {"n_dose1": 0, "n_cum_dose1": 0, "taux": 0.0}, "24": {"n_dose1": 0, "n_cum_dose1": 0, "taux": 0.0}, "74": {"n_dose1": 0, "n_cum_dose1": 0, "taux": 0.0}, "29": {"n_dose1": 0, "n_cum_dose1": 0, "taux": 0.0}, "0": {"n_dose1": 0, "n_cum_dose1": 0, "taux": 0.0}, "59": {"n_dose1": 0, "n_cum_dose1": 0, "taux": 0.0}, "79": {"n_dose1": 0, "n_cum_dose1": 0, "taux": 0.0}, "64": {"n_dose1": 0, "n_cum_dose1": 0, "taux": 0.0}, "69": {"n_dose1": 0, "n_cum_dose1": 0, "taux": 0.0}, "49": {"n_dose1": 0, "n_cum_dose1": 0, "taux": 0.0}}, "2021-01-11": {"80": {"n_dose1": 21, "n_cum_dose1": 223, "taux": "0.33"}, "39": {"n_dose1": 82, "n_cum_dose1": 180, "taux": "0.11"}, "24": {"n_dose1": 12, "n_cum_dose1": 25, "taux": "0.01"}, "74": {"n_dose1": 66, "n_cum_dose1": 202, "taux": "0.40"}, "29": {"n_dose1": 24, "n_cum_dose1": 48, "taux": "0.07"}, "0": {"n_dose1": 771, "n_cum_dose1": 2803, "taux": "0.22"}, "59": {"n_dose1": 261, "n_cum_dose1": 983, "taux": "0.60"}, "79": {"n_dose1": 18, "n_cum_dose1": 100, "taux": "0.26"}, "64": {"n_dose1": 135, "n_cum_dose1": 528, "taux": "0.73"}, "69": {"n_dose1": 63, "n_cum_dose1": 272, "taux": "0.40"}, "49": {"n_dose1": 89, "n_cum_dose1": 241, "taux": "0.14"}}, "2021-01-12": {"80": {"n_dose1": 351, "n_cum_dose1": 574, "taux": "0.85"}, "39": {"n_dose1": 110, "n_cum_dose1": 290, "taux": "0.18"}, "24": {"n_dose1": 12, "n_cum_dose1": 37, "taux": "0.02"}, "74": {"n_dose1": 55, "n_cum_dose1": 257, "taux": "0.50"}, "29": {"n_dose1": 21, "n_cum_dose1": 69, "taux": "0.10"}, "0": {"n_dose1": 1387, "n_cum_dose1": 4190, "taux": "0.33"}, "59": {"n_dose1": 373, "n_cum_dose1": 1356, "taux": "0.83"}, "79": {"n_dose1": 59, "n_cum_dose1": 159, "taux": "0.41"}, "64": {"n_dose1": 162, "n_cum_dose1": 690, "taux": "0.96"}, "69": {"n_dose1": 82, "n_cum_dose1": 354, "taux": "0.52"}, "49": {"n_dose1": 162, "n_cum_dose1": 403, "taux": "0.23"}}, "2021-01-13": {"80": {"n_dose1": 176, "n_cum_dose1": 750, "taux": "1.12"}, "39": {"n_dose1": 68, "n_cum_dose1": 358, "taux": "0.23"}, "24": {"n_dose1": 8, "n_cum_dose1": 45, "taux": "0.02"}, "74": {"n_dose1": 37, "n_cum_dose1": 294, "taux": "0.58"}, "29": {"n_dose1": 30, "n_cum_dose1": 99, "taux": "0.14"}, "0": {"n_dose1": 958, "n_cum_dose1": 5148, "taux": "0.41"}, "59": {"n_dose1": 305, "n_cum_dose1": 1661, "taux": "1.02"}, "79": {"n_dose1": 57, "n_cum_dose1": 216, "taux": "0.55"}, "64": {"n_dose1": 138, "n_cum_dose1": 828, "taux": "1.15"}, "69": {"n_dose1": 68, "n_cum_dose1": 422, "taux": "0.62"}, "49": {"n_dose1": 71, "n_cum_dose1": 474, "taux": "0.28"}}, "2021-01-14": {"80": {"n_dose1": 431, "n_cum_dose1": 1181, "taux": "1.76"}, "39": {"n_dose1": 120, "n_cum_dose1": 478, "taux": "0.30"}, "24": {"n_dose1": 9, "n_cum_dose1": 54, "taux": "0.02"}, "74": {"n_dose1": 91, "n_cum_dose1": 385, "taux": "0.75"}, "29": {"n_dose1": 40, "n_cum_dose1": 139, "taux": "0.20"}, "0": {"n_dose1": 1564, "n_cum_dose1": 6712, "taux": "0.53"}, "59": {"n_dose1": 354, "n_cum_dose1": 2015, "taux": "1.24"}, "79": {"n_dose1": 90, "n_cum_dose1": 306, "taux": "0.79"}, "64": {"n_dose1": 170, "n_cum_dose1": 998, "taux": "1.38"}, "69": {"n_dose1": 114, "n_cum_dose1": 536, "taux": "0.79"}, "49": {"n_dose1": 145, "n_cum_dose1": 619, "taux": "0.36"}}, "2021-01-15": {"80": {"n_dose1": 395, "n_cum_dose1": 1576, "taux": "2.35"}, "39": {"n_dose1": 97, "n_cum_dose1": 575, "taux": "0.37"}, "24": {"n_dose1": 9, "n_cum_dose1": 63, "taux": "0.03"}, "74": {"n_dose1": 84, "n_cum_dose1": 469, "taux": "0.92"}, "29": {"n_dose1": 22, "n_cum_dose1": 161, "taux": "0.23"}, "0": {"n_dose1": 1451, "n_cum_dose1": 8163, "taux": "0.65"}, "59": {"n_dose1": 343, "n_cum_dose1": 2358, "taux": "1.45"}, "79": {"n_dose1": 126, "n_cum_dose1": 432, "taux": "1.11"}, "64": {"n_dose1": 137, "n_cum_dose1": 1135, "taux": "1.57"}, "69": {"n_dose1": 89, "n_cum_dose1": 625, "taux": "0.92"}, "49": {"n_dose1": 149, "n_cum_dose1": 768, "taux": "0.45"}}, "2021-01-16": {"80": {"n_dose1": 52, "n_cum_dose1": 1628, "taux": "2.42"}, "39": {"n_dose1": 10, "n_cum_dose1": 585, "taux": "0.37"}, "24": {"n_dose1": 1, "n_cum_dose1": 64, "taux": "0.03"}, "74": {"n_dose1": 37, "n_cum_dose1": 506, "taux": "0.99"}, "29": {"n_dose1": 4, "n_cum_dose1": 165, "taux": "0.23"}, "0": {"n_dose1": 302, "n_cum_dose1": 8465, "taux": "0.67"}, "59": {"n_dose1": 83, "n_cum_dose1": 2441, "taux": "1.50"}, "79": {"n_dose1": 26, "n_cum_dose1": 458, "taux": "1.18"}, "64": {"n_dose1": 29, "n_cum_dose1": 1164, "taux": "1.61"}, "69": {"n_dose1": 44, "n_cum_dose1": 669, "taux": "0.98"}, "49": {"n_dose1": 16, "n_cum_dose1": 784, "taux": "0.46"}}, "2021-01-17": {"80": {"n_dose1": 2, "n_cum_dose1": 1630, "taux": "2.43"}, "39": {"n_dose1": 0, "n_cum_dose1": 0, "taux": 0.0}, "24": {"n_dose1": 0, "n_cum_dose1": 0, "taux": 0.0}, "74": {"n_dose1": 0, "n_cum_dose1": 0, "taux": 0.0}, "29": {"n_dose1": 0, "n_cum_dose1": 0, "taux": 0.0}, "0": {"n_dose1": 3, "n_cum_dose1": 8468, "taux": "0.67"}, "59": {"n_dose1": 1, "n_cum_dose1": 2442, "taux": "1.50"}, "79": {"n_dose1": 0, "n_cum_dose1": 0, "taux": 0.0}, "64": {"n_dose1": 0, "n_cum_dose1": 0, "taux": 0.0}, "69": {"n_dose1": 0, "n_cum_dose1": 0, "taux": 0.0}, "49": {"n_dose1": 0, "n_cum_dose1": 0, "taux": 0.0}}, "2021-01-18": {"80": {"n_dose1": 434, "n_cum_dose1": 2064, "taux": "3.07"}, "39": {"n_dose1": 40, "n_cum_dose1": 625, "taux": "0.40"}, "24": {"n_dose1": 10, "n_cum_dose1": 74, "taux": "0.03"}, "74": {"n_dose1": 39, "n_cum_dose1": 545, "taux": "1.07"}, "29": {"n_dose1": 15, "n_cum_dose1": 180, "taux": "0.26"}, "0": {"n_dose1": 1100, "n_cum_dose1": 9568, "taux": "0.76"}, "59": {"n_dose1": 108, "n_cum_dose1": 2550, "taux": "1.57"}, "79": {"n_dose1": 303, "n_cum_dose1": 761, "taux": "1.95"}, "64": {"n_dose1": 54, "n_cum_dose1": 1218, "taux": "1.69"}, "69": {"n_dose1": 44, "n_cum_dose1": 713, "taux": "1.05"}, "49": {"n_dose1": 53, "n_cum_dose1": 837, "taux": "0.49"}}, "2021-01-19": {"80": {"n_dose1": 1056, "n_cum_dose1": 3120, "taux": "4.64"}, "39": {"n_dose1": 62, "n_cum_dose1": 687, "taux": "0.44"}, "24": {"n_dose1": 4, "n_cum_dose1": 78, "taux": "0.03"}, "74": {"n_dose1": 103, "n_cum_dose1": 648, "taux": "1.27"}, "29": {"n_dose1": 16, "n_cum_dose1": 196, "taux": "0.28"}, "0": {"n_dose1": 2081, "n_cum_dose1": 11649, "taux": "0.93"}, "59": {"n_dose1": 219, "n_cum_dose1": 2769, "taux": "1.70"}, "79": {"n_dose1": 367, "n_cum_dose1": 1128, "taux": "2.90"}, "64": {"n_dose1": 111, "n_cum_dose1": 1329, "taux": "1.84"}, "69": {"n_dose1": 66, "n_cum_dose1": 779, "taux": "1.15"}, "49": {"n_dose1": 77, "n_cum_dose1": 914, "taux": "0.53"}}, "2021-01-20": {"80": {"n_dose1": 875, "n_cum_dose1": 3995, "taux": "5.94"}, "39": {"n_dose1": 46, "n_cum_dose1": 733, "taux": "0.47"}, "24": {"n_dose1": 15, "n_cum_dose1": 93, "taux": "0.04"}, "74": {"n_dose1": 53, "n_cum_dose1": 701, "taux": "1.37"}, "29": {"n_dose1": 24, "n_cum_dose1": 220, "taux": "0.31"}, "0": {"n_dose1": 1780, "n_cum_dose1": 13429, "taux": "1.07"}, "59": {"n_dose1": 212, "n_cum_dose1": 2981, "taux": "1.83"}, "79": {"n_dose1": 355, "n_cum_dose1": 1483, "taux": "3.81"}, "64": {"n_dose1": 71, "n_cum_dose1": 1400, "taux": "1.94"}, "69": {"n_dose1": 38, "n_cum_dose1": 817, "taux": "1.20"}, "49": {"n_dose1": 91, "n_cum_dose1": 1005, "taux": "0.58"}}, "2021-01-21": {"80": {"n_dose1": 634, "n_cum_dose1": 4629, "taux": "6.89"}, "39": {"n_dose1": 50, "n_cum_dose1": 783, "taux": "0.50"}, "24": {"n_dose1": 6, "n_cum_dose1": 99, "taux": "0.04"}, "74": {"n_dose1": 57, "n_cum_dose1": 758, "taux": "1.48"}, "29": {"n_dose1": 10, "n_cum_dose1": 230, "taux": "0.33"}, "0": {"n_dose1": 1470, "n_cum_dose1": 14899, "taux": "1.18"}, "59": {"n_dose1": 180, "n_cum_dose1": 3161, "taux": "1.94"}, "79": {"n_dose1": 333, "n_cum_dose1": 1816, "taux": "4.67"}, "64": {"n_dose1": 53, "n_cum_dose1": 1453, "taux": "2.01"}, "69": {"n_dose1": 48, "n_cum_dose1": 865, "taux": "1.27"}, "49": {"n_dose1": 99, "n_cum_dose1": 1104, "taux": "0.64"}}, "2021-01-22": {"80": {"n_dose1": 594, "n_cum_dose1": 5223, "taux": "7.77"}, "39": {"n_dose1": 26, "n_cum_dose1": 809, "taux": "0.52"}, "24": {"n_dose1": 4, "n_cum_dose1": 103, "taux": "0.04"}, "74": {"n_dose1": 54, "n_cum_dose1": 812, "taux": "1.59"}, "29": {"n_dose1": 10, "n_cum_dose1": 240, "taux": "0.34"}, "0": {"n_dose1": 1246, "n_cum_dose1": 16145, "taux": "1.28"}, "59": {"n_dose1": 106, "n_cum_dose1": 3267, "taux": "2.01"}, "79": {"n_dose1": 315, "n_cum_dose1": 2131, "taux": "5.47"}, "64": {"n_dose1": 49, "n_cum_dose1": 1502, "taux": "2.08"}, "69": {"n_dose1": 41, "n_cum_dose1": 906, "taux": "1.33"}, "49": {"n_dose1": 47, "n_cum_dose1": 1151, "taux": "0.67"}}, "2021-01-23": {"80": {"n_dose1": 204, "n_cum_dose1": 5427, "taux": "8.08"}, "39": {"n_dose1": 2, "n_cum_dose1": 811, "taux": "0.52"}, "24": {"n_dose1": 0, "n_cum_dose1": 0, "taux": 0.0}, "74": {"n_dose1": 14, "n_cum_dose1": 826, "taux": "1.62"}, "29": {"n_dose1": 0, "n_cum_dose1": 0, "taux": 0.0}, "0": {"n_dose1": 377, "n_cum_dose1": 16522, "taux": "1.31"}, "59": {"n_dose1": 14, "n_cum_dose1": 3281, "taux": "2.02"}, "79": {"n_dose1": 117, "n_cum_dose1": 2248, "taux": "5.77"}, "64": {"n_dose1": 11, "n_cum_dose1": 1513, "taux": "2.10"}, "69": {"n_dose1": 12, "n_cum_dose1": 918, "taux": "1.35"}, "49": {"n_dose1": 3, "n_cum_dose1": 1154, "taux": "0.67"}}, "2021-01-24": {"80": {"n_dose1": 0, "n_cum_dose1": 0, "taux": 0.0}, "39": {"n_dose1": 0, "n_cum_dose1": 0, "taux": 0.0}, "24": {"n_dose1": 0, "n_cum_dose1": 0, "taux": 0.0}, "74": {"n_dose1": 0, "n_cum_dose1": 0, "taux": 0.0}, "29": {"n_dose1": 0, "n_cum_dose1": 0, "taux": 0.0}, "0": {"n_dose1": 1, "n_cum_dose1": 16523, "taux": "1.31"}, "59": {"n_dose1": 1, "n_cum_dose1": 3282, "taux": "2.02"}, "79": {"n_dose1": 0, "n_cum_dose1": 0, "taux": 0.0}, "64": {"n_dose1": 0, "n_cum_dose1": 0, "taux": 0.0}, "69": {"n_dose1": 0, "n_cum_dose1": 0, "taux": 0.0}, "49": {"n_dose1": 0, "n_cum_dose1": 0, "taux": 0.0}}, "2021-01-25": {"80": {"n_dose1": 365, "n_cum_dose1": 5792, "taux": "8.62"}, "39": {"n_dose1": 6, "n_cum_dose1": 817, "taux": "0.52"}, "24": {"n_dose1": 1, "n_cum_dose1": 104, "taux": "0.04"}, "74": {"n_dose1": 21, "n_cum_dose1": 847, "taux": "1.66"}, "29": {"n_dose1": 6, "n_cum_dose1": 246, "taux": "0.35"}, "0": {"n_dose1": 777, "n_cum_dose1": 17300, "taux": "1.37"}, "59": {"n_dose1": 60, "n_cum_dose1": 3342, "taux": "2.06"}, "79": {"n_dose1": 247, "n_cum_dose1": 2495, "taux": "6.41"}, "64": {"n_dose1": 28, "n_cum_dose1": 1541, "taux": "2.13"}, "69": {"n_dose1": 16, "n_cum_dose1": 934, "taux": "1.37"}, "49": {"n_dose1": 27, "n_cum_dose1": 1181, "taux": "0.69"}}, "2021-01-26": {"80": {"n_dose1": 411, "n_cum_dose1": 6203, "taux": "9.23"}, "39": {"n_dose1": 12, "n_cum_dose1": 829, "taux": "0.53"}, "24": {"n_dose1": 0, "n_cum_dose1": 104, "taux": "0.04"}, "74": {"n_dose1": 34, "n_cum_dose1": 881, "taux": "1.72"}, "29": {"n_dose1": 1, "n_cum_dose1": 247, "taux": "0.35"}, "0": {"n_dose1": 828, "n_cum_dose1": 18128, "taux": "1.44"}, "59": {"n_dose1": 43, "n_cum_dose1": 3385, "taux": "2.08"}, "79": {"n_dose1": 259, "n_cum_dose1": 2754, "taux": "7.07"}, "64": {"n_dose1": 30, "n_cum_dose1": 1571, "taux": "2.18"}, "69": {"n_dose1": 15, "n_cum_dose1": 949, "taux": "1.40"}, "49": {"n_dose1": 23, "n_cum_dose1": 1204, "taux": "0.70"}}, "2021-01-27": {"80": {"n_dose1": 603, "n_cum_dose1": 6806, "taux": "10.13"}, "39": {"n_dose1": 12, "n_cum_dose1": 841, "taux": "0.54"}, "24": {"n_dose1": 4, "n_cum_dose1": 108, "taux": "0.04"}, "74": {"n_dose1": 42, "n_cum_dose1": 923, "taux": "1.81"}, "29": {"n_dose1": 3, "n_cum_dose1": 250, "taux": "0.35"}, "0": {"n_dose1": 1056, "n_cum_dose1": 19184, "taux": "1.52"}, "59": {"n_dose1": 41, "n_cum_dose1": 3426, "taux": "2.11"}, "79": {"n_dose1": 283, "n_cum_dose1": 3037, "taux": "7.80"}, "64": {"n_dose1": 25, "n_cum_dose1": 1596, "taux": "2.21"}, "69": {"n_dose1": 29, "n_cum_dose1": 978, "taux": "1.44"}, "49": {"n_dose1": 14, "n_cum_dose1": 1218, "taux": "0.71"}}, "2021-01-28": {"80": {"n_dose1": 549, "n_cum_dose1": 7355, "taux": "10.94"}, "39": {"n_dose1": 17, "n_cum_dose1": 858, "taux": "0.55"}, "24": {"n_dose1": 3, "n_cum_dose1": 111, "taux": "0.05"}, "74": {"n_dose1": 48, "n_cum_dose1": 971, "taux": "1.90"}, "29": {"n_dose1": 3, "n_cum_dose1": 253, "taux": "0.36"}, "0": {"n_dose1": 1058, "n_cum_dose1": 20242, "taux": "1.61"}, "59": {"n_dose1": 53, "n_cum_dose1": 3479, "taux": "2.14"}, "79": {"n_dose1": 283, "n_cum_dose1": 3320, "taux": "8.53"}, "64": {"n_dose1": 23, "n_cum_dose1": 1619, "taux": "2.24"}, "69": {"n_dose1": 32, "n_cum_dose1": 1010, "taux": "1.49"}, "49": {"n_dose1": 46, "n_cum_dose1": 1264, "taux": "0.74"}}, "2021-01-29": {"80": {"n_dose1": 444, "n_cum_dose1": 7799, "taux": "11.61"}, "39": {"n_dose1": 23, "n_cum_dose1": 881, "taux": "0.56"}, "24": {"n_dose1": 7, "n_cum_dose1": 118, "taux": "0.05"}, "74": {"n_dose1": 46, "n_cum_dose1": 1017, "taux": "1.99"}, "29": {"n_dose1": 15, "n_cum_dose1": 268, "taux": "0.38"}, "0": {"n_dose1": 883, "n_cum_dose1": 21125, "taux": "1.68"}, "59": {"n_dose1": 28, "n_cum_dose1": 3507, "taux": "2.16"}, "79": {"n_dose1": 237, "n_cum_dose1": 3557, "taux": "9.14"}, "64": {"n_dose1": 25, "n_cum_dose1": 1644, "taux": "2.28"}, "69": {"n_dose1": 25, "n_cum_dose1": 1035, "taux": "1.52"}, "49": {"n_dose1": 33, "n_cum_dose1": 1297, "taux": "0.75"}}, "2021-01-30": {"80": {"n_dose1": 170, "n_cum_dose1": 7969, "taux": "11.86"}, "39": {"n_dose1": 2, "n_cum_dose1": 883, "taux": "0.56"}, "24": {"n_dose1": 0, "n_cum_dose1": 0, "taux": 0.0}, "74": {"n_dose1": 5, "n_cum_dose1": 1022, "taux": "2.00"}, "29": {"n_dose1": 1, "n_cum_dose1": 269, "taux": "0.38"}, "0": {"n_dose1": 300, "n_cum_dose1": 21425, "taux": "1.70"}, "59": {"n_dose1": 4, "n_cum_dose1": 3511, "taux": "2.16"}, "79": {"n_dose1": 110, "n_cum_dose1": 3667, "taux": "9.42"}, "64": {"n_dose1": 5, "n_cum_dose1": 1649, "taux": "2.28"}, "69": {"n_dose1": 2, "n_cum_dose1": 1037, "taux": "1.53"}, "49": {"n_dose1": 1, "n_cum_dose1": 1298, "taux": "0.76"}}, "2021-01-31": {"80": {"n_dose1": 0, "n_cum_dose1": 0, "taux": 0.0}, "39": {"n_dose1": 0, "n_cum_dose1": 0, "taux": 0.0}, "24": {"n_dose1": 0, "n_cum_dose1": 0, "taux": 0.0}, "74": {"n_dose1": 0, "n_cum_dose1": 0, "taux": 0.0}, "29": {"n_dose1": 0, "n_cum_dose1": 0, "taux": 0.0}, "0": {"n_dose1": 0, "n_cum_dose1": 0, "taux": 0.0}, "59": {"n_dose1": 0, "n_cum_dose1": 0, "taux": 0.0}, "79": {"n_dose1": 0, "n_cum_dose1": 0, "taux": 0.0}, "64": {"n_dose1": 0, "n_cum_dose1": 0, "taux": 0.0}, "69": {"n_dose1": 0, "n_cum_dose1": 0, "taux": 0.0}, "49": {"n_dose1": 0, "n_cum_dose1": 0, "taux": 0.0}}, "2021-02-01": {"80": {"n_dose1": 330, "n_cum_dose1": 8299, "taux": "12.35"}, "39": {"n_dose1": 15, "n_cum_dose1": 898, "taux": "0.57"}, "24": {"n_dose1": 1, "n_cum_dose1": 119, "taux": "0.05"}, "74": {"n_dose1": 27, "n_cum_dose1": 1049, "taux": "2.05"}, "29": {"n_dose1": 5, "n_cum_dose1": 274, "taux": "0.39"}, "0": {"n_dose1": 649, "n_cum_dose1": 22074, "taux": "1.75"}, "59": {"n_dose1": 48, "n_cum_dose1": 3559, "taux": "2.19"}, "79": {"n_dose1": 176, "n_cum_dose1": 3843, "taux": "9.87"}, "64": {"n_dose1": 17, "n_cum_dose1": 1666, "taux": "2.31"}, "69": {"n_dose1": 20, "n_cum_dose1": 1057, "taux": "1.56"}, "49": {"n_dose1": 9, "n_cum_dose1": 1307, "taux": "0.76"}}, "2021-02-02": {"80": {"n_dose1": 473, "n_cum_dose1": 8772, "taux": "13.05"}, "39": {"n_dose1": 19, "n_cum_dose1": 917, "taux": "0.58"}, "24": {"n_dose1": 2, "n_cum_dose1": 121, "taux": "0.05"}, "74": {"n_dose1": 44, "n_cum_dose1": 1093, "taux": "2.14"}, "29": {"n_dose1": 5, "n_cum_dose1": 279, "taux": "0.40"}, "0": {"n_dose1": 847, "n_cum_dose1": 22921, "taux": "1.82"}, "59": {"n_dose1": 43, "n_cum_dose1": 3602, "taux": "2.22"}, "79": {"n_dose1": 179, "n_cum_dose1": 4022, "taux": "10.33"}, "64": {"n_dose1": 25, "n_cum_dose1": 1691, "taux": "2.34"}, "69": {"n_dose1": 22, "n_cum_dose1": 1079, "taux": "1.59"}, "49": {"n_dose1": 34, "n_cum_dose1": 1341, "taux": "0.78"}}, "2021-02-03": {"80": {"n_dose1": 601, "n_cum_dose1": 9373, "taux": "13.95"}, "39": {"n_dose1": 12, "n_cum_dose1": 929, "taux": "0.59"}, "24": {"n_dose1": 5, "n_cum_dose1": 126, "taux": "0.05"}, "74": {"n_dose1": 41, "n_cum_dose1": 1134, "taux": "2.22"}, "29": {"n_dose1": 6, "n_cum_dose1": 285, "taux": "0.40"}, "0": {"n_dose1": 1076, "n_cum_dose1": 23997, "taux": "1.91"}, "59": {"n_dose1": 82, "n_cum_dose1": 3684, "taux": "2.27"}, "79": {"n_dose1": 238, "n_cum_dose1": 4260, "taux": "10.94"}, "64": {"n_dose1": 27, "n_cum_dose1": 1718, "taux": "2.38"}, "69": {"n_dose1": 33, "n_cum_dose1": 1112, "taux": "1.64"}, "49": {"n_dose1": 31, "n_cum_dose1": 1372, "taux": "0.80"}}, "2021-02-04": {"80": {"n_dose1": 510, "n_cum_dose1": 9883, "taux": "14.71"}, "39": {"n_dose1": 30, "n_cum_dose1": 959, "taux": "0.61"}, "24": {"n_dose1": 3, "n_cum_dose1": 129, "taux": "0.05"}, "74": {"n_dose1": 50, "n_cum_dose1": 1184, "taux": "2.32"}, "29": {"n_dose1": 9, "n_cum_dose1": 294, "taux": "0.42"}, "0": {"n_dose1": 1106, "n_cum_dose1": 25103, "taux": "1.99"}, "59": {"n_dose1": 73, "n_cum_dose1": 3757, "taux": "2.31"}, "79": {"n_dose1": 285, "n_cum_dose1": 4545, "taux": "11.68"}, "64": {"n_dose1": 52, "n_cum_dose1": 1770, "taux": "2.45"}, "69": {"n_dose1": 44, "n_cum_dose1": 1156, "taux": "1.70"}, "49": {"n_dose1": 49, "n_cum_dose1": 1421, "taux": "0.83"}}, "2021-02-05": {"80": {"n_dose1": 563, "n_cum_dose1": 10446, "taux": "15.54"}, "39": {"n_dose1": 34, "n_cum_dose1": 993, "taux": "0.63"}, "24": {"n_dose1": 8, "n_cum_dose1": 137, "taux": "0.06"}, "74": {"n_dose1": 57, "n_cum_dose1": 1241, "taux": "2.43"}, "29": {"n_dose1": 8, "n_cum_dose1": 302, "taux": "0.43"}, "0": {"n_dose1": 1102, "n_cum_dose1": 26205, "taux": "2.08"}, "59": {"n_dose1": 62, "n_cum_dose1": 3819, "taux": "2.35"}, "79": {"n_dose1": 275, "n_cum_dose1": 4820, "taux": "12.38"}, "64": {"n_dose1": 32, "n_cum_dose1": 1802, "taux": "2.50"}, "69": {"n_dose1": 27, "n_cum_dose1": 1183, "taux": "1.74"}, "49": {"n_dose1": 36, "n_cum_dose1": 1457, "taux": "0.85"}}}