{"0": {"n_tot_dose1": 81204, "n_tot_dose2": 37402, "rate_dose1": 4.01, "rate_dose2": 1.85}, "24": {"n_tot_dose1": 500, "n_tot_dose2": 229, "rate_dose1": 0.14, "rate_dose2": 0.06}, "29": {"n_tot_dose1": 1183, "n_tot_dose2": 644, "rate_dose1": 1.01, "rate_dose2": 0.55}, "39": {"n_tot_dose1": 3181, "n_tot_dose2": 1889, "rate_dose1": 1.27, "rate_dose2": 0.75}, "49": {"n_tot_dose1": 4697, "n_tot_dose2": 2860, "rate_dose1": 1.78, "rate_dose2": 1.08}, "59": {"n_tot_dose1": 9960, "n_tot_dose2": 6583, "rate_dose1": 3.78, "rate_dose2": 2.5}, "64": {"n_tot_dose1": 5286, "n_tot_dose2": 3306, "rate_dose1": 4.4, "rate_dose2": 2.75}, "69": {"n_tot_dose1": 4313, "n_tot_dose2": 2216, "rate_dose1": 3.7, "rate_dose2": 1.9}, "74": {"n_tot_dose1": 5143, "n_tot_dose2": 2232, "rate_dose1": 5.55, "rate_dose2": 2.41}, "79": {"n_tot_dose1": 15808, "n_tot_dose2": 5602, "rate_dose1": 22.3, "rate_dose2": 7.9}, "80": {"n_tot_dose1": 31115, "n_tot_dose2": 11839, "rate_dose1": 24.91, "rate_dose2": 9.48}}